silorider/__init__.py
silorider/config.py
silorider/default.cfg
silorider/format.py
silorider/format.py.orig
silorider/main.py
silorider/parse.py
silorider/version.py
silorider/__pycache__/__init__.cpython-36.pyc
silorider/__pycache__/__init__.cpython-39.pyc
silorider/__pycache__/config.cpython-36.pyc
silorider/__pycache__/config.cpython-39.pyc
silorider/__pycache__/format.cpython-36.pyc
silorider/__pycache__/format.cpython-39.pyc
silorider/__pycache__/main.cpython-36.pyc
silorider/__pycache__/main.cpython-39.pyc
silorider/__pycache__/parse.cpython-36.pyc
silorider/__pycache__/parse.cpython-39.pyc
silorider/__pycache__/parsehelper.cpython-36.pyc
silorider/__pycache__/processor.cpython-36.pyc
silorider/cache/__init__.py
silorider/cache/base.py
silorider/cache/memory.py
silorider/cache/sqlite.py
silorider/cache/__pycache__/__init__.cpython-36.pyc
silorider/cache/__pycache__/__init__.cpython-39.pyc
silorider/cache/__pycache__/base.cpython-36.pyc
silorider/cache/__pycache__/base.cpython-39.pyc
silorider/cache/__pycache__/memory.cpython-36.pyc
silorider/cache/__pycache__/memory.cpython-39.pyc
silorider/cache/__pycache__/sqlite.cpython-36.pyc
silorider/commands/__init__.py
silorider/commands/auth.py
silorider/commands/process.py
silorider/commands/utils.py
silorider/commands/__pycache__/__init__.cpython-36.pyc
silorider/commands/__pycache__/__init__.cpython-39.pyc
silorider/commands/__pycache__/auth.cpython-36.pyc
silorider/commands/__pycache__/process.cpython-36.pyc
silorider/commands/__pycache__/process.cpython-39.pyc
silorider/commands/__pycache__/utils.cpython-36.pyc
silorider/commands/__pycache__/utils.cpython-39.pyc
silorider/silos/__init__.py
silorider/silos/base.py
silorider/silos/mastodon.py
silorider/silos/print.py
silorider/silos/twitter.py
silorider/silos/webmention.py
silorider/silos/__pycache__/__init__.cpython-36.pyc
silorider/silos/__pycache__/__init__.cpython-39.pyc
silorider/silos/__pycache__/base.cpython-36.pyc
SiloRider-0.2.1.dist-info/LICENSE.rst
SiloRider-0.2.1.dist-info/METADATA
SiloRider-0.2.1.dist-info/WHEEL
SiloRider-0.2.1.dist-info/entry_points.txt
SiloRider-0.2.1.dist-info/top_level.txt
SiloRider-0.2.1.dist-info/RECORD
