Metadata-Version: 2.1
Name: SiloRider
Version: 0.2.1
Summary: Scans a website's microformats and cross-posts content to 'silo' services.
Home-page: https://bolt80.com/silorider
Author: Ludovic Chabant
Author-email: ludovic@chabant.com
License: Apache License 2.0
License-File: LICENSE.rst
Requires-Dist: coloredlogs (>=10.0)
Requires-Dist: Mastodon.py (>=1.3.0)
Requires-Dist: mf2py (>=1.1.0)
Requires-Dist: mf2util (>=0.5.0)
Requires-Dist: python-dateutil (>=2.7.0)
Requires-Dist: python-twitter (>=3.4.0)
Requires-Dist: ronkyuu (>=0.6)
